vfbLib/__init__.py
vfbLib/_version.py
vfbLib/cmdline.py
vfbLib/constants.py
vfbLib/cu2qu.py
vfbLib/diff.py
vfbLib/enum.py
vfbLib/helpers.py
vfbLib/json.py
vfbLib/truetype.py
vfbLib/tth.py
vfbLib/typing.py
vfbLib/value.py
vfbLib/compilers/__init__.py
vfbLib/compilers/base.py
vfbLib/compilers/binary.py
vfbLib/compilers/bitmap.py
vfbLib/compilers/cmap.py
vfbLib/compilers/fl3.py
vfbLib/compilers/glyph.py
vfbLib/compilers/guides.py
vfbLib/compilers/header.py
vfbLib/compilers/mm.py
vfbLib/compilers/numeric.py
vfbLib/compilers/options.py
vfbLib/compilers/pclt.py
vfbLib/compilers/ps.py
vfbLib/compilers/text.py
vfbLib/compilers/truetype.py
vfbLib/compilers/value.py
vfbLib/parsers/__init__.py
vfbLib/parsers/base.py
vfbLib/parsers/binary.py
vfbLib/parsers/bitmap.py
vfbLib/parsers/cmap.py
vfbLib/parsers/fl3.py
vfbLib/parsers/glyph.py
vfbLib/parsers/guides.py
vfbLib/parsers/header.py
vfbLib/parsers/mm.py
vfbLib/parsers/numeric.py
vfbLib/parsers/options.py
vfbLib/parsers/pclt.py
vfbLib/parsers/ps.py
vfbLib/parsers/text.py
vfbLib/parsers/truetype.py
vfbLib/parsers/value.py
vfbLib/templates/__init__.py
vfbLib/templates/glyph.py
vfbLib/ufo/__init__.py
vfbLib/ufo/builder.py
vfbLib/ufo/designspace.py
vfbLib/ufo/features.py
vfbLib/ufo/glyph.py
vfbLib/ufo/groups.py
vfbLib/ufo/guides.py
vfbLib/ufo/info.py
vfbLib/ufo/kerning.py
vfbLib/ufo/paths.py
vfbLib/ufo/pshints.py
vfbLib/ufo/time.py
vfbLib/ufo/tth.py
vfbLib/ufo/typing.py
vfbLib/ufo/vfb2ufo.py
vfbLib/vfb/__init__.py
vfbLib/vfb/entry.py
vfbLib/vfb/glyph.py
vfbLib/vfb/header.py
vfbLib/vfb/info.py
vfbLib/vfb/pens.py
vfbLib/vfb/vfb.py
vfblib-0.10.6.dist-info/licenses/LICENSE
vfblib-0.10.6.dist-info/METADATA
vfblib-0.10.6.dist-info/WHEEL
vfblib-0.10.6.dist-info/entry_points.txt
vfblib-0.10.6.dist-info/top_level.txt
vfblib-0.10.6.dist-info/RECORD
